AUTHORS.md
CHANGES.md
INSTALL.md
LICENSE
MANIFEST.in
README.md
pyproject.toml
setup.py
cryptofeed/__init__.py
cryptofeed/callback.py
cryptofeed/config.py
cryptofeed/connection.py
cryptofeed/connection_handler.py
cryptofeed/defines.py
cryptofeed/exceptions.py
cryptofeed/exchange.py
cryptofeed/feed.py
cryptofeed/feedhandler.py
cryptofeed/log.py
cryptofeed/nbbo.py
cryptofeed/raw_data_collection.py
cryptofeed/symbols.py
cryptofeed/types.c
cryptofeed/types.pyx
cryptofeed/auth/__init__.py
cryptofeed/auth/okcoin.py
cryptofeed/auth/okex.py
cryptofeed/backends/__init__.py
cryptofeed/backends/_util.py
cryptofeed/backends/aggregate.py
cryptofeed/backends/arctic.py
cryptofeed/backends/backend.py
cryptofeed/backends/elastic.py
cryptofeed/backends/gcppubsub.py
cryptofeed/backends/http.py
cryptofeed/backends/influxdb.py
cryptofeed/backends/kafka.py
cryptofeed/backends/mongo.py
cryptofeed/backends/postgres.py
cryptofeed/backends/rabbitmq.py
cryptofeed/backends/redis.py
cryptofeed/backends/socket.py
cryptofeed/backends/victoriametrics.py
cryptofeed/backends/zmq.py
cryptofeed/exchanges/__init__.py
cryptofeed/exchanges/ascendex.py
cryptofeed/exchanges/bequant.py
cryptofeed/exchanges/binance.py
cryptofeed/exchanges/binance_delivery.py
cryptofeed/exchanges/binance_futures.py
cryptofeed/exchanges/binance_us.py
cryptofeed/exchanges/bitfinex.py
cryptofeed/exchanges/bitflyer.py
cryptofeed/exchanges/bithumb.py
cryptofeed/exchanges/bitmex.py
cryptofeed/exchanges/bitstamp.py
cryptofeed/exchanges/bittrex.py
cryptofeed/exchanges/blockchain.py
cryptofeed/exchanges/bybit.py
cryptofeed/exchanges/coinbase.py
cryptofeed/exchanges/deribit.py
cryptofeed/exchanges/dydx.py
cryptofeed/exchanges/exx.py
cryptofeed/exchanges/fmfw.py
cryptofeed/exchanges/ftx.py
cryptofeed/exchanges/ftx_us.py
cryptofeed/exchanges/gateio.py
cryptofeed/exchanges/gemini.py
cryptofeed/exchanges/hitbtc.py
cryptofeed/exchanges/huobi.py
cryptofeed/exchanges/huobi_dm.py
cryptofeed/exchanges/huobi_swap.py
cryptofeed_yas.egg-info/PKG-INFO
cryptofeed_yas.egg-info/SOURCES.txt
cryptofeed_yas.egg-info/dependency_links.txt
cryptofeed_yas.egg-info/requires.txt
cryptofeed_yas.egg-info/top_level.txt