Metadata-Version: 2.1
Name: cryptofeed-yas
Version: 0.0.1
Summary: Cryptocurrency Exchange Websocket Data Feed Handler
Home-page: https://github.com/bmoscon/cryptofeed
Author: Hooman Radmehr
Author-email: hooman.radmehr.dev@gmail.com
License: XFree86
Keywords: cryptocurrency,bitcoin,btc,feed handler,market feed,market data,crypto assets,Trades,Tickers,BBO,Funding,Open Interest,Liquidation,Order book,Bid,Ask,fmfw.io,Bitfinex,bitFlyer,AscendEX,Bitstamp,Bittrex,Blockchain.com,Bybit,Binance,Binance Delivery,Binance Futures,Binance US,BitMEX,Coinbase,Deribit,EXX,FTX,FTX US,Gate.io,Gemini,HitBTC,Huobi,Huobi DM,Huobi Swap,Kraken,Kraken Futures,OKCoin,OKEx,Poloniex,ProBit,Upbit
Platform: UNKNOWN
Classifier: Intended Audience :: Developers
Classifier: Development Status :: 4 - Beta
Classifier: Programming Language :: Python :: 3 :: Only
Classifier: Programming Language :: Python :: 3.7
Classifier: Programming Language :: Python :: 3.8
Classifier: Programming Language :: Python :: 3.9
Classifier: Framework :: AsyncIO
Requires-Python: >=3.7
Provides-Extra: arctic
Provides-Extra: gcp_pubsub
Provides-Extra: kafka
Provides-Extra: mongo
Provides-Extra: postgres
Provides-Extra: rabbit
Provides-Extra: redis
Provides-Extra: zmq
Provides-Extra: all
License-File: LICENSE
License-File: AUTHORS.md
